flashdeconv/__init__.py
flashdeconv/core/__init__.py
flashdeconv/core/deconv.py
flashdeconv/core/sketching.py
flashdeconv/core/solver.py
flashdeconv/core/spatial.py
flashdeconv/io/__init__.py
flashdeconv/io/loader.py
flashdeconv/tl/__init__.py
flashdeconv/tl/_deconvolve.py
flashdeconv/utils/__init__.py
flashdeconv/utils/genes.py
flashdeconv/utils/graph.py
flashdeconv/utils/metrics.py
flashdeconv/utils/random.py
flashdeconv/utils/sparse.py
flashdeconv-0.1.4.dist-info/licenses/LICENSE
flashdeconv-0.1.4.dist-info/METADATA
flashdeconv-0.1.4.dist-info/WHEEL
flashdeconv-0.1.4.dist-info/top_level.txt
flashdeconv-0.1.4.dist-info/RECORD
