Metadata-Version: 2.4
Name: flashdeconv
Version: 0.1.4
Summary: Fast Linear Algebra for Scalable Hybrid Deconvolution of Spatial Transcriptomics
Author: FlashDeconv Team
License: BSD-3-Clause
Project-URL: Homepage, https://github.com/cafferychen777/flashdeconv
Project-URL: Documentation, https://github.com/cafferychen777/flashdeconv
Project-URL: Repository, https://github.com/cafferychen777/flashdeconv
Project-URL: Paper, https://doi.org/10.64898/2025.12.22.696108
Keywords: spatial transcriptomics,deconvolution,single-cell,bioinformatics,computational biology
Classifier: Development Status :: 3 - Alpha
Classifier: Intended Audience :: Science/Research
Classifier: License :: OSI Approved :: BSD License
Classifier: Programming Language :: Python :: 3
Classifier: Programming Language :: Python :: 3.9
Classifier: Programming Language :: Python :: 3.10
Classifier: Programming Language :: Python :: 3.11
Classifier: Programming Language :: Python :: 3.12
Classifier: Topic :: Scientific/Engineering :: Bio-Informatics
Requires-Python: >=3.9
License-File: LICENSE
Requires-Dist: numpy>=1.21
Requires-Dist: scipy>=1.7
Requires-Dist: numba>=0.56
Provides-Extra: io
Requires-Dist: anndata>=0.8; extra == "io"
Requires-Dist: pandas>=1.3; extra == "io"
Provides-Extra: dev
Requires-Dist: pytest>=7.0; extra == "dev"
Requires-Dist: pytest-cov>=4.0; extra == "dev"
Requires-Dist: black>=23.0; extra == "dev"
Requires-Dist: isort>=5.0; extra == "dev"
Requires-Dist: mypy>=1.0; extra == "dev"
Provides-Extra: scanpy
Requires-Dist: scanpy>=1.9; extra == "scanpy"
Provides-Extra: all
Requires-Dist: flashdeconv[dev,io,scanpy]; extra == "all"
Dynamic: license-file
